Metadata-Version: 1.0
Name: simpler-ansi2html
Version: 0.1.0
Summary: an alternative ansi2html
Home-page: https://github.com/volodymyrss/pystatuscake.git
Author: M. Bravo (Kronuz), Volodymyr Savchenko
Author-email: vladimir.savchenko@gmail.com
License: UNKNOWN
Platform: UNKNOWN
